{"total_tracks":1694,"unique_tracks":1445,"unique_artists":952,"first_track_at":"2026-07-13T13:27:34Z","last_track_at":"2026-07-14T10:40:38Z","tracks_by_date":[{"date":"2026-07-13","count":848},{"date":"2026-07-14","count":846}],"non_music":[{"station_id":1,"station_name":"קול השפלה 103.6FM","station_slug":"kol-hashfela","event_count":98,"total_seconds":1963.000014424324,"last_event_at":"2026-07-14T10:01:04Z"},{"station_id":2,"station_name":"גלגלצ","station_slug":"galgalatz","event_count":364,"total_seconds":6784.000499546528,"last_event_at":"2026-07-14T10:42:22Z"},{"station_id":3,"station_name":"99FM","station_slug":"99fm","event_count":387,"total_seconds":7447.000162303448,"last_event_at":"2026-07-14T10:39:02Z"},{"station_id":4,"station_name":"רדיו תל אביב 102FM","station_slug":"radio-tlv","event_count":321,"total_seconds":6232.999907433987,"last_event_at":"2026-07-14T10:39:42Z"},{"station_id":5,"station_name":"כאן 88","station_slug":"kan-88","event_count":921,"total_seconds":18370.999811589718,"last_event_at":"2026-07-14T10:31:24Z"},{"station_id":6,"station_name":"כאן ב","station_slug":"kan-bet","event_count":1359,"total_seconds":26633.999893069267,"last_event_at":"2026-07-14T10:42:02Z"},{"station_id":7,"station_name":"קול הגליל העליון","station_slug":"galil","event_count":585,"total_seconds":11504.000003635883,"last_event_at":"2026-07-14T10:01:04Z"},{"station_id":8,"station_name":"רדיו דרום 97FM","station_slug":"radio-darom","event_count":801,"total_seconds":15984.000004827976,"last_event_at":"2026-07-14T10:42:02Z"}],"repeat_data":{"epoch":"2026-07-13T18:05:00Z","hours_collected":16.6,"min_hours_required":48,"trusted_tracks":1398,"ready":false},"tracks_today":1147,"busiest_hour":23,"most_active_station_today":"kol-hashfela","updated_at":"2026-07-14T10:42:23Z"}
